LICENSE
MANIFEST.in
README.rst
requirements.txt
setup.cfg
setup.py
synapse_ldap_password_provider.py
tox.ini
synapse_ldap_password_provider.egg-info/PKG-INFO
synapse_ldap_password_provider.egg-info/SOURCES.txt
synapse_ldap_password_provider.egg-info/dependency_links.txt
synapse_ldap_password_provider.egg-info/requires.txt
synapse_ldap_password_provider.egg-info/top_level.txt
tests/__init__.py
tests/ldap_server.py
tests/test_simple.py