Metadata-Version: 1.1
Name: synapse-ldap-password-provider
Version: 1
Summary: LDAP3 password provider for Synapse
Home-page: https://github.com/slipeer/synapse-ldap-password-provider
Author: Slipeer
Author-email: slipeer@gmail.com
License: UNKNOWN
Download-URL: https://github.com/slipeer/synapse-ldap-password-provider/archive/1.0.tar.gz
Platform: UNKNOWN
Classifier: Development Status :: 4 - Beta
Classifier: Environment :: Plugins
Classifier: License :: OSI Approved :: Apache Software License
Classifier: Programming Language :: Python :: 2
Classifier: Topic :: Communications :: Chat
